<?xml version="1.0" encoding="UTF-8"?>
<objects serializationModel="Studio.01.09.00">
    <object class="Event" id="{b249ac96-1728-4a50-bdfb-68f12a1f9e44}">
        <property name="name">
            <value>Ataque_Forte_Liz</value>
        </property>
        <property name="outputFormat">
            <value>2</value>
        </property>
        <relationship name="folder">
            <destination>{65fc7274-0158-40be-9493-75623f060fb0}</destination>
        </relationship>
        <relationship name="mixer">
            <destination>{80f08445-5b01-4b8d-a3d1-e35e38d96a26}</destination>
        </relationship>
        <relationship name="masterTrack">
            <destination>{0774b836-ed1a-4e60-bf59-5e662f41c8c6}</destination>
        </relationship>
        <relationship name="mixerInput">
            <destination>{b1bf66d5-4ee0-4c19-b624-a76b3749662f}</destination>
        </relationship>
        <relationship name="automatableProperties">
            <destination>{0837111f-b79a-472c-9b5b-eaf843ead90a}</destination>
        </relationship>
        <relationship name="markerTracks">
            <destination>{c154c64a-a6e5-4741-854e-7b92fd7e757b}</destination>
        </relationship>
        <relationship name="groupTracks">
            <destination>{43969076-f6b7-4d16-8150-a2f0380a0134}</destination>
        </relationship>
        <relationship name="timeline">
            <destination>{e91946e2-0f89-4b11-ac86-790c96ce97df}</destination>
        </relationship>
    </object>
    <object class="EventMixer" id="{80f08445-5b01-4b8d-a3d1-e35e38d96a26}">
        <relationship name="masterBus">
            <destination>{a8d42aae-1cf3-4ca5-8d55-3dafda846148}</destination>
        </relationship>
    </object>
    <object class="MasterTrack" id="{0774b836-ed1a-4e60-bf59-5e662f41c8c6}">
        <relationship name="mixerGroup">
            <destination>{a8d42aae-1cf3-4ca5-8d55-3dafda846148}</destination>
        </relationship>
    </object>
    <object class="MixerInput" id="{b1bf66d5-4ee0-4c19-b624-a76b3749662f}">
        <relationship name="effectChain">
            <destination>{a763f670-04f1-4977-a424-2cab8f57579a}</destination>
        </relationship>
        <relationship name="panner">
            <destination>{3fe6344a-10a5-4eb3-a437-af43db7b1c51}</destination>
        </relationship>
        <relationship name="output">
            <destination>{f58d2150-9fad-4aa0-8621-f3dba9c2ee89}</destination>
        </relationship>
    </object>
    <object class="EventAutomatableProperties" id="{0837111f-b79a-472c-9b5b-eaf843ead90a}"/>
    <object class="MarkerTrack" id="{c154c64a-a6e5-4741-854e-7b92fd7e757b}"/>
    <object class="GroupTrack" id="{43969076-f6b7-4d16-8150-a2f0380a0134}">
        <relationship name="mixerGroup">
            <destination>{a77fb769-a618-41c6-9220-561c08f190fa}</destination>
        </relationship>
    </object>
    <object class="Timeline" id="{e91946e2-0f89-4b11-ac86-790c96ce97df}"/>
    <object class="EventMixerMaster" id="{a8d42aae-1cf3-4ca5-8d55-3dafda846148}">
        <relationship name="effectChain">
            <destination>{678c589f-fee1-4ae0-b405-c46e9dd92f23}</destination>
        </relationship>
        <relationship name="panner">
            <destination>{217d9e9c-14fd-45a7-a983-d1882947b086}</destination>
        </relationship>
        <relationship name="mixer">
            <destination>{80f08445-5b01-4b8d-a3d1-e35e38d96a26}</destination>
        </relationship>
    </object>
    <object class="MixerBusEffectChain" id="{a763f670-04f1-4977-a424-2cab8f57579a}">
        <relationship name="effects">
            <destination>{3c013da0-cf58-4e1a-9b2f-7d6b2f532a6e}</destination>
        </relationship>
    </object>
    <object class="MixerBusPanner" id="{3fe6344a-10a5-4eb3-a437-af43db7b1c51}"/>
    <object class="EventMixerGroup" id="{a77fb769-a618-41c6-9220-561c08f190fa}">
        <property name="name">
            <value>Audio 1</value>
        </property>
        <relationship name="effectChain">
            <destination>{c1a810ff-0b59-46f7-a25c-cbec8fc1e0bf}</destination>
        </relationship>
        <relationship name="panner">
            <destination>{1c702f62-82f2-433f-86a9-95569ccd4867}</destination>
        </relationship>
        <relationship name="output">
            <destination>{a8d42aae-1cf3-4ca5-8d55-3dafda846148}</destination>
        </relationship>
    </object>
    <object class="MixerBusEffectChain" id="{678c589f-fee1-4ae0-b405-c46e9dd92f23}">
        <relationship name="effects">
            <destination>{2a515f79-2ff9-4d9a-9d3c-47dd1e9f8774}</destination>
            <destination>{b4c01cfa-a8c3-48c3-99c0-8482e1989dda}</destination>
        </relationship>
    </object>
    <object class="MixerBusPanner" id="{217d9e9c-14fd-45a7-a983-d1882947b086}"/>
    <object class="MixerBusFader" id="{3c013da0-cf58-4e1a-9b2f-7d6b2f532a6e}"/>
    <object class="MixerBusEffectChain" id="{c1a810ff-0b59-46f7-a25c-cbec8fc1e0bf}">
        <relationship name="effects">
            <destination>{bdca9ce2-bc7d-4e61-94a3-192e30a9fe5c}</destination>
        </relationship>
    </object>
    <object class="MixerBusPanner" id="{1c702f62-82f2-433f-86a9-95569ccd4867}"/>
    <object class="MixerBusFader" id="{2a515f79-2ff9-4d9a-9d3c-47dd1e9f8774}"/>
    <object class="SpatialiserEffect" id="{b4c01cfa-a8c3-48c3-99c0-8482e1989dda}"/>
    <object class="MixerBusFader" id="{bdca9ce2-bc7d-4e61-94a3-192e30a9fe5c}"/>
</objects>
