<?xml version="1.0" encoding="UTF-8"?>
<objects serializationModel="Studio.01.09.00">
    <object class="Event" id="{cb76b373-0211-4874-82de-f3d02935bab7}">
        <property name="name">
            <value>Get_Damage_Mosquito</value>
        </property>
        <property name="outputFormat">
            <value>2</value>
        </property>
        <relationship name="folder">
            <destination>{21bafcee-330e-47a8-b3e9-649e917e870c}</destination>
        </relationship>
        <relationship name="mixer">
            <destination>{c23cc3df-7cd4-4706-bac5-026513f04da7}</destination>
        </relationship>
        <relationship name="masterTrack">
            <destination>{967c5bde-1913-4457-90bc-65dca8f78391}</destination>
        </relationship>
        <relationship name="mixerInput">
            <destination>{18eff90d-7527-4c8e-9f8b-65cbb5980823}</destination>
        </relationship>
        <relationship name="automatableProperties">
            <destination>{daeccf45-7cfb-4029-96db-e8bcefd61d84}</destination>
        </relationship>
        <relationship name="markerTracks">
            <destination>{49e0f34f-4b26-4ee7-8ead-d8a1c154587c}</destination>
        </relationship>
        <relationship name="groupTracks">
            <destination>{0d4ef258-8aa3-4e4d-aedf-15489cf15909}</destination>
        </relationship>
        <relationship name="timeline">
            <destination>{505d8ff8-a793-43c2-b272-ea19d946ef20}</destination>
        </relationship>
    </object>
    <object class="EventMixer" id="{c23cc3df-7cd4-4706-bac5-026513f04da7}">
        <relationship name="masterBus">
            <destination>{ae120f36-7942-4d11-ba5e-7f2a379198f1}</destination>
        </relationship>
    </object>
    <object class="MasterTrack" id="{967c5bde-1913-4457-90bc-65dca8f78391}">
        <relationship name="mixerGroup">
            <destination>{ae120f36-7942-4d11-ba5e-7f2a379198f1}</destination>
        </relationship>
    </object>
    <object class="MixerInput" id="{18eff90d-7527-4c8e-9f8b-65cbb5980823}">
        <relationship name="effectChain">
            <destination>{2d4881c7-e197-4a56-a817-cb56ca14138f}</destination>
        </relationship>
        <relationship name="panner">
            <destination>{4da8cc17-29a2-4feb-abcd-4db3e4cd4f36}</destination>
        </relationship>
        <relationship name="output">
            <destination>{f58d2150-9fad-4aa0-8621-f3dba9c2ee89}</destination>
        </relationship>
    </object>
    <object class="EventAutomatableProperties" id="{daeccf45-7cfb-4029-96db-e8bcefd61d84}"/>
    <object class="MarkerTrack" id="{49e0f34f-4b26-4ee7-8ead-d8a1c154587c}"/>
    <object class="GroupTrack" id="{0d4ef258-8aa3-4e4d-aedf-15489cf15909}">
        <relationship name="mixerGroup">
            <destination>{ddac2e0b-8d41-45b9-abf5-d5df7931a87b}</destination>
        </relationship>
    </object>
    <object class="Timeline" id="{505d8ff8-a793-43c2-b272-ea19d946ef20}"/>
    <object class="EventMixerMaster" id="{ae120f36-7942-4d11-ba5e-7f2a379198f1}">
        <relationship name="effectChain">
            <destination>{5ce791eb-26b3-498d-9932-55a0ba734222}</destination>
        </relationship>
        <relationship name="panner">
            <destination>{a864d944-6538-421e-bd89-c56b43c0b190}</destination>
        </relationship>
        <relationship name="mixer">
            <destination>{c23cc3df-7cd4-4706-bac5-026513f04da7}</destination>
        </relationship>
    </object>
    <object class="MixerBusEffectChain" id="{2d4881c7-e197-4a56-a817-cb56ca14138f}">
        <relationship name="effects">
            <destination>{4c27152a-6c8c-438b-94be-0102b371a7c6}</destination>
        </relationship>
    </object>
    <object class="MixerBusPanner" id="{4da8cc17-29a2-4feb-abcd-4db3e4cd4f36}"/>
    <object class="EventMixerGroup" id="{ddac2e0b-8d41-45b9-abf5-d5df7931a87b}">
        <property name="name">
            <value>Audio 1</value>
        </property>
        <relationship name="effectChain">
            <destination>{55813961-5192-4b7e-bf99-ce8c49aa2b64}</destination>
        </relationship>
        <relationship name="panner">
            <destination>{be578853-6a9f-4eb9-920c-b6bfacaa39fd}</destination>
        </relationship>
        <relationship name="output">
            <destination>{ae120f36-7942-4d11-ba5e-7f2a379198f1}</destination>
        </relationship>
    </object>
    <object class="MixerBusEffectChain" id="{5ce791eb-26b3-498d-9932-55a0ba734222}">
        <relationship name="effects">
            <destination>{33b3d842-957a-47a6-9cc8-06e174381965}</destination>
            <destination>{759b2e52-8099-47d6-a087-d643841fcbb7}</destination>
        </relationship>
    </object>
    <object class="MixerBusPanner" id="{a864d944-6538-421e-bd89-c56b43c0b190}"/>
    <object class="MixerBusFader" id="{4c27152a-6c8c-438b-94be-0102b371a7c6}"/>
    <object class="MixerBusEffectChain" id="{55813961-5192-4b7e-bf99-ce8c49aa2b64}">
        <relationship name="effects">
            <destination>{2d8a9800-e12a-4b5b-99c8-fd520f8180a8}</destination>
        </relationship>
    </object>
    <object class="MixerBusPanner" id="{be578853-6a9f-4eb9-920c-b6bfacaa39fd}"/>
    <object class="MixerBusFader" id="{33b3d842-957a-47a6-9cc8-06e174381965}"/>
    <object class="SpatialiserEffect" id="{759b2e52-8099-47d6-a087-d643841fcbb7}"/>
    <object class="MixerBusFader" id="{2d8a9800-e12a-4b5b-99c8-fd520f8180a8}"/>
</objects>
